cepton_alg/__init__.py
cepton_alg/api.py
cepton_alg/c.py
cepton_alg/core.py
cepton_alg/frame.py
cepton_alg/load.py
cepton_alg/render.py
cepton_alg/render_mask.py
cepton_alg/viewer.py
cepton_alg/common/__init__.py
cepton_alg/common/c.py
cepton_alg/common/capture.py
cepton_alg/common/geometry.py
cepton_alg/common/gui.py
cepton_alg/common/math.py
cepton_alg/common/render.py
cepton_alg/common/render_sdk.py
cepton_alg/common/render_vispy.py
cepton_alg/common/time.py
cepton_alg/common/transform.py
cepton_alg/common/viewer_sdk.py
cepton_alg/common/meshes/car.stl
cepton_alg/settings/alg/default.json
cepton_alg/settings/alg/drive.json
cepton_alg/settings/alg/indoor.json
cepton_alg/settings/alg/surfaces.json
cepton_alg/settings/alg/tracking_drive.json
cepton_alg/settings/alg/tracking_indoor.json
cepton_alg/settings/alg/tracking_outdoor.json
cepton_alg/settings/alg/tracking_stationary_indoor.json
cepton_alg/settings/alg/tracking_stationary_outdoor.json
cepton_alg/settings/render/default.json
cepton_alg-0.2.10.data/scripts/cepton_alg_render.py
cepton_alg-0.2.10.data/scripts/cepton_alg_viewer.py
cepton_alg-0.2.10.data/scripts/cepton_player.py
cepton_alg-0.2.10.dist-info/DESCRIPTION.rst
cepton_alg-0.2.10.dist-info/METADATA
cepton_alg-0.2.10.dist-info/RECORD
cepton_alg-0.2.10.dist-info/WHEEL
cepton_alg-0.2.10.dist-info/metadata.json
cepton_alg-0.2.10.dist-info/top_level.txt
cepton_alg_redist/__init__.py
